sphinxnotes/incrbuild/__init__.py
sphinxnotes/incrbuild/__main__.py
sphinxnotes/incrbuild/meta.py
sphinxnotes/incrbuild/py.typed
sphinxnotes/incrbuild/sphinxapi.py
sphinxnotes/incrbuild/utils.py
sphinxnotes/incrbuild/git-tools/git-restore-mtime
sphinxnotes_incrbuild-1.1.dist-info/licenses/LICENSE
sphinxnotes_incrbuild-1.1.dist-info/METADATA
sphinxnotes_incrbuild-1.1.dist-info/WHEEL
sphinxnotes_incrbuild-1.1.dist-info/entry_points.txt
sphinxnotes_incrbuild-1.1.dist-info/top_level.txt
sphinxnotes_incrbuild-1.1.dist-info/RECORD
