Metadata-Version: 2.4
Name: sphinxnotes-incrbuild
Version: 1.1
Summary: Enabling Sphinx incremental builds in CI/CD environment
Author: Shengyu Zhang
Maintainer: Shengyu Zhang
License-Expression: BSD-3-Clause
Project-URL: homepage, https://sphinx.silverrainz.me/incrbuild
Project-URL: documentation, https://sphinx.silverrainz.me/incrbuild
Project-URL: repository, https://github.com/sphinx-notes/incrbuild
Project-URL: changelog, https://sphinx.silverrainz.me/incrbuild/changelog.html
Project-URL: tracker, https://github.com/sphinx-notes/incrbuild/issues
Keywords: sphinx,extension,documentation,sphinxnotes
Classifier: Development Status :: 3 - Alpha
Classifier: Operating System :: OS Independent
Classifier: Programming Language :: Python
Classifier: Programming Language :: Python :: 3
Classifier: Topic :: Documentation
Classifier: Topic :: Documentation :: Sphinx
Requires-Python: >=3.12
License-File: LICENSE
Requires-Dist: Sphinx>=7.0
Requires-Dist: colorama
Requires-Dist: pypi_simple
Requires-Dist: packaging
Provides-Extra: dev
Requires-Dist: build; extra == "dev"
Requires-Dist: twine; extra == "dev"
Requires-Dist: cruft; extra == "dev"
Requires-Dist: ruff>=0.11.10; extra == "dev"
Requires-Dist: pre-commit; extra == "dev"
Provides-Extra: test
Requires-Dist: pytest; extra == "test"
Provides-Extra: docs
Requires-Dist: furo; extra == "docs"
Requires-Dist: sphinx_design; extra == "docs"
Requires-Dist: sphinx_copybutton; extra == "docs"
Requires-Dist: sphinxcontrib-gtagjs; extra == "docs"
Requires-Dist: sphinx-sitemap; extra == "docs"
Requires-Dist: sphinxext-opengraph; extra == "docs"
Requires-Dist: sphinx-last-updated-by-git; extra == "docs"
Requires-Dist: sphinxnotes-project; extra == "docs"
Requires-Dist: sphinxnotes-comboroles; extra == "docs"
Dynamic: license-file
